README
setup.py
ftpbenchmark/__init__.py
ftpbenchmark/ftpbenchmark.py
ftpbenchmark.egg-info/PKG-INFO
ftpbenchmark.egg-info/SOURCES.txt
ftpbenchmark.egg-info/dependency_links.txt
ftpbenchmark.egg-info/entry_points.txt
ftpbenchmark.egg-info/requires.txt
ftpbenchmark.egg-info/top_level.txt